Workbook

Sheet Cost per clause
A1: Provider | B1: LLM | C1: Input cost per 1M tokens | D1: Output cost per 1M tokens | E1: Cost per clause (typical) | F1: Category
A2: ='Pricing & cost per clause'!A2 | B2: ='Pricing & cost per clause'!B2 | C2: ='Pricing & cost per clause'!D2 | D2: ='Pricing & cost per clause'!F2 | E2: ='Pricing & cost per clause'!I2 | F2: -
A3: ='Pricing & cost per clause'!A3 | B3: ='Pricing & cost per clause'!B3 | C3: ='Pricing & cost per clause'!D3 | D3: ='Pricing & cost per clause'!F3 | E3: ='Pricing & cost per clause'!I3 | F3: Chinese LLM
A4: ='Pricing & cost per clause'!A4 | B4: ='Pricing & cost per clause'!B4 | C4: ='Pricing & cost per clause'!D4 | D4: ='Pricing & cost per clause'!F4 | E4: ='Pricing & cost per clause'!I4 | F4: -
A5: ='Pricing & cost per clause'!A5 | B5: ='Pricing & cost per clause'!B5 | C5: ='Pricing & cost per clause'!D5 | D5: ='Pricing & cost per clause'!F5 | E5: ='Pricing & cost per clause'!I5 | F5: Chinese LLM
A6: ='Pricing & cost per clause'!A6 | B6: ='Pricing & cost per clause'!B6 | C6: ='Pricing & cost per clause'!D6 | D6: ='Pricing & cost per clause'!F6 | E6: ='Pricing & cost per clause'!I6 | F6: -
A7: ='Pricing & cost per clause'!A7 | B7: ='Pricing & cost per clause'!B7 | C7: ='Pricing & cost per clause'!D7 | D7: ='Pricing & cost per clause'!F7 | E7: ='Pricing & cost per clause'!I7 | F7: Chinese LLM
A8: ='Pricing & cost per clause'!A8 | B8: ='Pricing & cost per clause'!B8 | C8: ='Pricing & cost per clause'!D8 | D8: ='Pricing & cost per clause'!F8 | E8: ='Pricing & cost per clause'!I8 | F8: -
A9: ='Pricing & cost per clause'!A9 | B9: ='Pricing & cost per clause'!B9 | C9: ='Pricing & cost per clause'!D9 | D9: ='Pricing & cost per clause'!F9 | E9: ='Pricing & cost per clause'!I9 | F9: -
A10: ='Pricing & cost per clause'!A10 | B10: ='Pricing & cost per clause'!B10 | C10: ='Pricing & cost per clause'!D10 | D10: ='Pricing & cost per clause'!F10 | E10: ='Pricing & cost per clause'!I10 | F10: -
A11: ='Pricing & cost per clause'!A11 | B11: ='Pricing & cost per clause'!B11 | C11: ='Pricing & cost per clause'!D11 | D11: ='Pricing & cost per clause'!F11 | E11: ='Pricing & cost per clause'!I11 | F11: Chinese LLM
A12: ='Pricing & cost per clause'!A12 | B12: ='Pricing & cost per clause'!B12 | C12: ='Pricing & cost per clause'!D12 | D12: ='Pricing & cost per clause'!F12 | E12: ='Pricing & cost per clause'!I12 | F12: Chinese LLM
A13: ='Pricing & cost per clause'!A13 | B13: ='Pricing & cost per clause'!B13 | C13: ='Pricing & cost per clause'!D13 | D13: ='Pricing & cost per clause'!F13 | E13: ='Pricing & cost per clause'!I13 | F13: Chinese LLM
... A38: ='Pricing & cost per clause'!A38 | B38: ='Pricing & cost per clause'!B38 | C38: ='Pricing & cost per clause'!D38 | D38: ='Pricing & cost per clause'!F38 | E38: ='Pricing & cost per clause'!I38 | F38: -
A40: Typical clause = 11,541 input + 1,310 output tokens (average of 3 real logged calls). Edit tokens and prices in the other sheets.
A41: Use the Category filter (column F header) to show only Chinese LLM rows, or open the dedicated 'Chinese LLMs' sheet.

Sheet Chinese LLMs
A1: Chinese LLM providers - cost per clause
A2: DeepSeek, Moonshot (Kimi) and Zhipu AI (GLM) are Chinese labs; Alibaba (Qwen) is Chinese too. None of these are wired into the app yet except Moonshot, whose account currently has no balance. Data for all of these is processed on China-hosted infrastructure - confirm the client's data policy before using one on real documents.
A4: Provider | B4: LLM | C4: Input $/1M | D4: Output $/1M | E4: Cost per clause | F4: Why
A5: Zhipu AI | B5: ='Pricing & cost per clause'!B11 | C5: ='Pricing & cost per clause'!D11 | D5: ='Pricing & cost per clause'!F11 | E5: ='Pricing & cost per clause'!I11 | F5: Cheapest of the three main Chinese labs; OpenAI-compatible API.
A6: Alibaba | B6: ='Pricing & cost per clause'!B3 | C6: ='Pricing & cost per clause'!D3 | D6: ='Pricing & cost per clause'!F3 | E6: ='Pricing & cost per clause'!I3 | F6: Very cheap but a lighter model.
A7: Alibaba | B7: ='Pricing & cost per clause'!B12 | C7: ='Pricing & cost per clause'!D12 | D7: ='Pricing & cost per clause'!F12 | E7: ='Pricing & cost per clause'!I12 | F7: Similar price to GLM-4.6.
A8: DeepSeek | B8: ='Pricing & cost per clause'!B5 | C8: ='Pricing & cost per clause'!D5 | D8: ='Pricing & cost per clause'!F5 | E8: ='Pricing & cost per clause'!I5 | F8: Already wired into our app, no key yet.
A9: Alibaba | B9: ='Pricing & cost per clause'!B26 | C9: ='Pricing & cost per clause'!D26 | D9: ='Pricing & cost per clause'!F26 | E9: ='Pricing & cost per clause'!I26 | F9: Alibaba's strongest model.
A10: Moonshot | B10: ='Pricing & cost per clause'!B33 | C10: ='Pricing & cost per clause'!D33 | D10: ='Pricing & cost per clause'!F33 | E10: ='Pricing & cost per clause'!I33 | F10: Already wired into our app and account created; balance needed to run it.

Sheet Assumptions
A1: V5 judgment step - tokens per clause (Step 8 only)
A2: Measured from 3 real logged calls on claude-opus-5 (V5, TFS Guidelines v12 vs IMPTFS). Input = input_tokens + cache_write_tokens (caching is OFF by default now, so all input bills at the base rate).
A4: Scenario | B4: Input tokens / clause | C4: Output tokens / clause | D4: How it was derived
A5: Light clause | B5: 4879 | C5: 1356 | D5: Smallest logged call: 1,169 input + 3,710 cache-write; 1,356 output
A6: Typical clause | B6: =ROUND(AVERAGE(4879,13703,16042),0) | C6: =ROUND(AVERAGE(1356,1273,1302),0) | D6: Average of the three logged calls (input 4,879 / 13,703 / 16,042; output 1,356 / 1,273 / 1,302)
A7: Heavy clause | B7: 16042 | C7: 1302 | D7: Largest logged call: 939 input + 15,103 cache-write; 1,302 output
A9: Run sizes used in the tables
A10: Small run (clauses) | B10: 30
A11: Medium run (clauses) | B11: 100
A12: Large run (clauses) | B12: 1000
A14: Notes
A15: 1. Yellow cells with blue text are inputs - change them and every cost recalculates.
A16: 2. Token counts are Claude Opus 5 tokenizer counts. Other vendors tokenize differently; use the 'Token factor' column on the Pricing sheet to adjust (1.00 = same).
A17: 3. Output tokens include the model's reasoning/structured-tool output. Models that 'think' more will use more output tokens than the logged Opus 5 calls.
A18: 4. Clause context is ~5k-16k tokens, so every model is priced at its standard (<=200k context) tier.
A19: 5. Prices are list prices in USD per 1M tokens, read from each vendor's pricing page on 21 Sep 2026. Prices change - re-check before committing budget.
A20: 6. This estimates ONLY the judgment call. Steps 1-7 (expansion, BM25, embeddings, fusion, selection) run locally and cost $0 in model fees.
A21: 7. QUALITY IS NOT MEASURED HERE. Only claude-opus-5 has been run through our pipeline. The 'Tier' column is a price tier, not a benchmark result.

Sheet Recommendation
A1: Recommended LLMs to test for V5 judgment
A2: Ranked by price tier and fit for structured compliance judgment over retrieved policy text - NOT a measured accuracy ranking. Only Claude Opus 5 has been verified end to end on V5; run the others on the verified 30-clause TFS set and compare against manual results before switching.
A4: Rank | B4: LLM | C4: Cost per clause | D4: Why
A5: 1 | B5: Claude Opus 5 | C5: ='Pricing & cost per clause'!I35 | D5: Already verified end to end (clause 2.5 came back compliant at 93% confidence). Treat it as the reference to beat.
A6: 2 | B6: gpt-5.6-sol | C6: ='Pricing & cost per clause'!I34 | D6: Top-tier OpenAI model, a comparable class, and a useful second opinion.
A7: 3 | B7: Claude Sonnet 5 | C7: ='Pricing & cost per clause'!I27 | D7: Same prompts and tool format as Opus 5, so it is the easiest fair comparison. It costs 60% less.
A8: 4 | B8: Gemini 3.1 Pro Preview | C8: ='Pricing & cost per clause'!I29 | D8: Strong reasoning tier, but it is a preview model.
A9: 5 | B9: kimi-k3 | C9: ='Pricing & cost per clause'!I33 | D9: Worth a look, but it needs a new provider added first (done - awaiting account balance).
A10: 6 | B10: glm-4.6 | C10: ='Pricing & cost per clause'!I11 | D10: Cheapest of the credible Chinese models; needs a new provider added first.

Sheet Pricing & cost per clause
A1: Provider | B1: Model | C1: Tier | D1: Input $/1M | E1: Cached input $/1M | F1: Output $/1M | G1: Token factor | H1: Cost / clause - light | I1: Cost / clause - TYPICAL | J1: Cost / clause - heavy | K1: Cost - small run | L1: Cost - medium run | M1: Cost - large run | N1: vs Opus 5 (typical) | O1: Context | P1: Available in our app today? | Q1: Notes | R1: Source
A2: Google | B2: Gemini 2.5 Flash-Lite | C2: Budget | D2: 0.1 | E2: 0.01 | F2: 0.4 | G2: 1 | H2: =(Assumptions!$B$5*$G2*$D2+Assumptions!$C$5*$G2*$F2)/1000000 | I2: =(Assumptions!$B$6*$G2*$D2+Assumptions!$C$6*$G2*$F2)/1000000 | J2: =(Assumptions!$B$7*$G2*$D2+Assumptions!$C$7*$G2*$F2)/1000000 | K2: =$I2*Assumptions!$B$10 | L2: =$I2*Assumptions!$B$11 | M2: =$I2*Assumptions!$B$12 | N2: =$I2/$I$35 | O2: - | P2: Yes - selectable | R2: https://ai.google.dev/gemini-api/docs/pricing
A3: Alibaba (Qwen) | B3: qwen3.5-flash | C3: Budget | D3: 0.1 | E3: 0.03 | F3: 0.4 | G3: 1 | H3: =(Assumptions!$B$5*$G3*$D3+Assumptions!$C$5*$G3*$F3)/1000000 | I3: =(Assumptions!$B$6*$G3*$D3+Assumptions!$C$6*$G3*$F3)/1000000 | J3: =(Assumptions!$B$7*$G3*$D3+Assumptions!$C$7*$G3*$F3)/1000000 | K3: =$I3*Assumptions!$B$10 | L3: =$I3*Assumptions!$B$11 | M3: =$I3*Assumptions!$B$12 | N3: =$I3/$I$35 | O3: 1M | P3: No - new provider needed (OpenAI-compatible API via DashScope) | Q3: Chinese (Alibaba). Lightest/cheapest Qwen tier. | R3: https://www.eesel.ai/blog/qwen-pricing
A4: OpenAI | B4: gpt-4o-mini | C4: Budget | D4: 0.15 | E4: 0.075 | F4: 0.6 | G4: 1 | H4: =(Assumptions!$B$5*$G4*$D4+Assumptions!$C$5*$G4*$F4)/1000000 | I4: =(Assumptions!$B$6*$G4*$D4+Assumptions!$C$6*$G4*$F4)/1000000 | J4: =(Assumptions!$B$7*$G4*$D4+Assumptions!$C$7*$G4*$F4)/1000000 | K4: =$I4*Assumptions!$B$10 | L4: =$I4*Assumptions!$B$11 | M4: =$I4*Assumptions!$B$12 | N4: =$I4/$I$35 | O4: - | P4: Yes - selectable | Q4: Older model. | R4: https://developers.openai.com/api/docs/pricing
A5: DeepSeek | B5: deepseek-flash (off-peak) | C5: Budget | D5: 0.15 | E5: 0.003 | F5: 0.6 | G5: 1 | H5: =(Assumptions!$B$5*$G5*$D5+Assumptions!$C$5*$G5*$F5)/1000000 | I5: =(Assumptions!$B$6*$G5*$D5+Assumptions!$C$6*$G5*$F5)/1000000 | J5: =(Assumptions!$B$7*$G5*$D5+Assumptions!$C$7*$G5*$F5)/1000000 | K5: =$I5*Assumptions!$B$10 | L5: =$I5*Assumptions!$B$11 | M5: =$I5*Assumptions!$B$12 | N5: =$I5/$I$35 | O5: 1M | P5: No - new provider needed (OpenAI-compatible API) | Q5: Off-peak rate. | R5: https://api-docs.deepseek.com/quick_start/pricing
A6: OpenAI | B6: gpt-5.6-luna | C6: Budget | D6: 0.2 | E6: 0.02 | F6: 1.2 | G6: 1 | H6: =(Assumptions!$B$5*$G6*$D6+Assumptions!$C$5*$G6*$F6)/1000000 | I6: =(Assumptions!$B$6*$G6*$D6+Assumptions!$C$6*$G6*$F6)/1000000 | J6: =(Assumptions!$B$7*$G6*$D6+Assumptions!$C$7*$G6*$F6)/1000000 | K6: =$I6*Assumptions!$B$10 | L6: =$I6*Assumptions!$B$11 | M6: =$I6*Assumptions!$B$12 | N6: =$I6/$I$35 | O6: - | P6: No - add id (provider exists) | R6: https://developers.openai.com/api/docs/pricing
A7: DeepSeek | B7: deepseek-flash (peak) | C7: Budget | D7: 0.3 | E7: 0.006 | F7: 1.2 | G7: 1 | H7: =(Assumptions!$B$5*$G7*$D7+Assumptions!$C$5*$G7*$F7)/1000000 | I7: =(Assumptions!$B$6*$G7*$D7+Assumptions!$C$6*$G7*$F7)/1000000 | J7: =(Assumptions!$B$7*$G7*$D7+Assumptions!$C$7*$G7*$F7)/1000000 | K7: =$I7*Assumptions!$B$10 | L7: =$I7*Assumptions!$B$11 | M7: =$I7*Assumptions!$B$12 | N7: =$I7/$I$35 | O7: 1M | P7: No - new provider needed (OpenAI-compatible API) | Q7: Peak rate. | R7: https://api-docs.deepseek.com/quick_start/pricing
A8: OpenAI | B8: gpt-5-mini | C8: Budget | D8: 0.25 | E8: 0.025 | F8: 2 | G8: 1 | H8: =(Assumptions!$B$5*$G8*$D8+Assumptions!$C$5*$G8*$F8)/1000000 | I8: =(Assumptions!$B$6*$G8*$D8+Assumptions!$C$6*$G8*$F8)/1000000 | J8: =(Assumptions!$B$7*$G8*$D8+Assumptions!$C$7*$G8*$F8)/1000000 | K8: =$I8*Assumptions!$B$10 | L8: =$I8*Assumptions!$B$11 | M8: =$I8*Assumptions!$B$12 | N8: =$I8/$I$35 | O8: - | P8: No - add id (provider exists) | R8: https://developers.openai.com/api/docs/pricing
A9: Google | B9: Gemini 2.5 Flash | C9: Budget | D9: 0.3 | E9: 0.03 | F9: 2.5 | G9: 1 | H9: =(Assumptions!$B$5*$G9*$D9+Assumptions!$C$5*$G9*$F9)/1000000 | I9: =(Assumptions!$B$6*$G9*$D9+Assumptions!$C$6*$G9*$F9)/1000000 | J9: =(Assumptions!$B$7*$G9*$D9+Assumptions!$C$7*$G9*$F9)/1000000 | K9: =$I9*Assumptions!$B$10 | L9: =$I9*Assumptions!$B$11 | M9: =$I9*Assumptions!$B$12 | N9: =$I9/$I$35 | O9: - | P9: Yes - selectable | R9: https://ai.google.dev/gemini-api/docs/pricing
A10: Google | B10: Gemini 3.5 Flash-Lite | C10: Budget | D10: 0.3 | E10: 0.03 | F10: 2.5 | G10: 1 | H10: =(Assumptions!$B$5*$G10*$D10+Assumptions!$C$5*$G10*$F10)/1000000 | I10: =(Assumptions!$B$6*$G10*$D10+Assumptions!$C$6*$G10*$F10)/1000000 | J10: =(Assumptions!$B$7*$G10*$D10+Assumptions!$C$7*$G10*$F10)/1000000 | K10: =$I10*Assumptions!$B$10 | L10: =$I10*Assumptions!$B$11 | M10: =$I10*Assumptions!$B$12 | N10: =$I10/$I$35 | O10: - | P10: Yes - selectable | R10: https://ai.google.dev/gemini-api/docs/pricing
A11: Zhipu AI (GLM) | B11: glm-4.6 | C11: Budget | D11: 0.43 | E11: 0.11 | F11: 1.74 | G11: 1 | H11: =(Assumptions!$B$5*$G11*$D11+Assumptions!$C$5*$G11*$F11)/1000000 | I11: =(Assumptions!$B$6*$G11*$D11+Assumptions!$C$6*$G11*$F11)/1000000 | J11: =(Assumptions!$B$7*$G11*$D11+Assumptions!$C$7*$G11*$F11)/1000000 | K11: =$I11*Assumptions!$B$10 | L11: =$I11*Assumptions!$B$11 | M11: =$I11*Assumptions!$B$12 | N11: =$I11/$I$35 | O11: 200k | P11: No - new provider needed (OpenAI-compatible API) | Q11: Chinese (Zhipu AI / Tsinghua). Cache hits ~20-25% of input rate. | R11: https://www.clawrouters.com/blog/zhipu-glm-api-pricing-2026
A12: Alibaba (Qwen) | B12: qwen3.5-plus | C12: Budget | D12: 0.4 | E12: 0.1 | F12: 2.4 | G12: 1 | H12: =(Assumptions!$B$5*$G12*$D12+Assumptions!$C$5*$G12*$F12)/1000000 | I12: =(Assumptions!$B$6*$G12*$D12+Assumptions!$C$6*$G12*$F12)/1000000 | J12: =(Assumptions!$B$7*$G12*$D12+Assumptions!$C$7*$G12*$F12)/1000000 | K12: =$I12*Assumptions!$B$10 | L12: =$I12*Assumptions!$B$11 | M12: =$I12*Assumptions!$B$12 | N12: =$I12/$I$35 | O12: 1M | P12: No - new provider needed (OpenAI-compatible API via DashScope) | Q12: Chinese (Alibaba). 1M context. | R12: https://www.eesel.ai/blog/qwen-pricing
A13: DeepSeek | B13: deepseek-v4-pro (off-peak) | C13: Budget | D13: 0.66 | E13: 0.022 | F13: 1.98 | G13: 1 | H13: =(Assumptions!$B$5*$G13*$D13+Assumptions!$C$5*$G13*$F13)/1000000 | I13: =(Assumptions!$B$6*$G13*$D13+Assumptions!$C$6*$G13*$F13)/1000000 | J13: =(Assumptions!$B$7*$G13*$D13+Assumptions!$C$7*$G13*$F13)/1000000 | K13: =$I13*Assumptions!$B$10 | L13: =$I13*Assumptions!$B$11 | M13: =$I13*Assumptions!$B$12 | N13: =$I13/$I$35 | O13: 1M | P13: No - new provider needed (OpenAI-compatible API) | Q13: Off-peak: all other times incl. weekends. | R13: https://api-docs.deepseek.com/quick_start/pricing
A14: Google | B14: Gemini 3.6 Flash | C14: Budget | D14: 0.75 | E14: 0.075 | F14: 3.75 | G14: 1 | H14: =(Assumptions!$B$5*$G14*$D14+Assumptions!$C$5*$G14*$F14)/1000000 | I14: =(Assumptions!$B$6*$G14*$D14+Assumptions!$C$6*$G14*$F14)/1000000 | J14: =(Assumptions!$B$7*$G14*$D14+Assumptions!$C$7*$G14*$F14)/1000000 | K14: =$I14*Assumptions!$B$10 | L14: =$I14*Assumptions!$B$11 | M14: =$I14*Assumptions!$B$12 | N14: =$I14/$I$35 | O14: - | P14: Yes - selectable | Q14: Promo rate through 31 Dec 2026; doubles on 1 Jan 2027. | R14: https://ai.google.dev/gemini-api/docs/pricing
A15: OpenAI | B15: gpt-5.4-mini | C15: Budget | D15: 0.75 | E15: 0.075 | F15: 4.5 | G15: 1 | H15: =(Assumptions!$B$5*$G15*$D15+Assumptions!$C$5*$G15*$F15)/1000000 | I15: =(Assumptions!$B$6*$G15*$D15+Assumptions!$C$6*$G15*$F15)/1000000 | J15: =(Assumptions!$B$7*$G15*$D15+Assumptions!$C$7*$G15*$F15)/1000000 | K15: =$I15*Assumptions!$B$10 | L15: =$I15*Assumptions!$B$11 | M15: =$I15*Assumptions!$B$12 | N15: =$I15/$I$35 | O15: - | P15: No - add id (provider exists) | R15: https://developers.openai.com/api/docs/pricing
A16: Moonshot (Kimi) | B16: kimi-k2.7-code | C16: Budget | D16: 0.95 | E16: 0.19 | F16: 4 | G16: 1 | H16: =(Assumptions!$B$5*$G16*$D16+Assumptions!$C$5*$G16*$F16)/1000000 | I16: =(Assumptions!$B$6*$G16*$D16+Assumptions!$C$6*$G16*$F16)/1000000 | J16: =(Assumptions!$B$7*$G16*$D16+Assumptions!$C$7*$G16*$F16)/1000000 | K16: =$I16*Assumptions!$B$10 | L16: =$I16*Assumptions!$B$11 | M16: =$I16*Assumptions!$B$12 | N16: =$I16/$I$35 | O16: 262k | P16: No - new provider needed (OpenAI-compatible API) | Q16: Coding-tuned model. | R16: https://platform.kimi.ai/docs/pricing/chat
A17: Moonshot (Kimi) | B17: kimi-k2.6 | C17: Budget | D17: 0.95 | E17: 0.16 | F17: 4 | G17: 1 | H17: =(Assumptions!$B$5*$G17*$D17+Assumptions!$C$5*$G17*$F17)/1000000 | I17: =(Assumptions!$B$6*$G17*$D17+Assumptions!$C$6*$G17*$F17)/1000000 | J17: =(Assumptions!$B$7*$G17*$D17+Assumptions!$C$7*$G17*$F17)/1000000 | K17: =$I17*Assumptions!$B$10 | L17: =$I17*Assumptions!$B$11 | M17: =$I17*Assumptions!$B$12 | N17: =$I17/$I$35 | O17: 262k | P17: No - new provider needed (OpenAI-compatible API) | R17: https://platform.kimi.ai/docs/pricing/chat
A18: xAI | B18: grok-4.3 | C18: Budget | D18: 1.25 | E18: 0.2 | F18: 2.5 | G18: 1 | H18: =(Assumptions!$B$5*$G18*$D18+Assumptions!$C$5*$G18*$F18)/1000000 | I18: =(Assumptions!$B$6*$G18*$D18+Assumptions!$C$6*$G18*$F18)/1000000 | J18: =(Assumptions!$B$7*$G18*$D18+Assumptions!$C$7*$G18*$F18)/1000000 | K18: =$I18*Assumptions!$B$10 | L18: =$I18*Assumptions!$B$11 | M18: =$I18*Assumptions!$B$12 | N18: =$I18/$I$35 | O18: 1M | P18: No - app lists only grok-3/grok-2 | Q18: Rates shown are <200k context. | R18: https://docs.x.ai/docs/models
A19: Anthropic | B19: Claude Haiku 4.5 | C19: Budget | D19: 1 | E19: 0.1 | F19: 5 | G19: 1 | H19: =(Assumptions!$B$5*$G19*$D19+Assumptions!$C$5*$G19*$F19)/1000000 | I19: =(Assumptions!$B$6*$G19*$D19+Assumptions!$C$6*$G19*$F19)/1000000 | J19: =(Assumptions!$B$7*$G19*$D19+Assumptions!$C$7*$G19*$F19)/1000000 | K19: =$I19*Assumptions!$B$10 | L19: =$I19*Assumptions!$B$11 | M19: =$I19*Assumptions!$B$12 | N19: =$I19/$I$35 | O19: 200k | P19: Yes - selectable | Q19: Older tokenizer. | R19: https://platform.claude.com/docs/en/about-claude/pricing
A20: DeepSeek | B20: deepseek-v4-pro (peak) | C20: Budget | D20: 1.32 | E20: 0.044 | F20: 3.96 | G20: 1 | H20: =(Assumptions!$B$5*$G20*$D20+Assumptions!$C$5*$G20*$F20)/1000000 | I20: =(Assumptions!$B$6*$G20*$D20+Assumptions!$C$6*$G20*$F20)/1000000 | J20: =(Assumptions!$B$7*$G20*$D20+Assumptions!$C$7*$G20*$F20)/1000000 | K20: =$I20*Assumptions!$B$10 | L20: =$I20*Assumptions!$B$11 | M20: =$I20*Assumptions!$B$12 | N20: =$I20/$I$35 | O20: 1M | P20: No - new provider needed (OpenAI-compatible API) | Q20: Peak: 01-04 and 06-10 UTC, Mon-Fri. Off-peak is half. | R20: https://api-docs.deepseek.com/quick_start/pricing
A21: OpenAI | B21: gpt-5 | C21: Balanced | D21: 1.25 | E21: 0.125 | F21: 10 | G21: 1 | H21: =(Assumptions!$B$5*$G21*$D21+Assumptions!$C$5*$G21*$F21)/1000000 | I21: =(Assumptions!$B$6*$G21*$D21+Assumptions!$C$6*$G21*$F21)/1000000 | J21: =(Assumptions!$B$7*$G21*$D21+Assumptions!$C$7*$G21*$F21)/1000000 | K21: =$I21*Assumptions!$B$10 | L21: =$I21*Assumptions!$B$11 | M21: =$I21*Assumptions!$B$12 | N21: =$I21/$I$35 | O21: - | P21: Yes - selectable | R21: https://developers.openai.com/api/docs/pricing
A22: Google | B22: Gemini 2.5 Pro | C22: Balanced | D22: 1.25 | E22: 0.125 | F22: 10 | G22: 1 | H22: =(Assumptions!$B$5*$G22*$D22+Assumptions!$C$5*$G22*$F22)/1000000 | I22: =(Assumptions!$B$6*$G22*$D22+Assumptions!$C$6*$G22*$F22)/1000000 | J22: =(Assumptions!$B$7*$G22*$D22+Assumptions!$C$7*$G22*$F22)/1000000 | K22: =$I22*Assumptions!$B$10 | L22: =$I22*Assumptions!$B$11 | M22: =$I22*Assumptions!$B$12 | N22: =$I22/$I$35 | O22: - | P22: No - add id (provider exists) | Q22: Rates shown are <=200k context. | R22: https://ai.google.dev/gemini-api/docs/pricing
A23: Google | B23: Gemini 3.5 Flash | C23: Balanced | D23: 1.5 | E23: 0.15 | F23: 9 | G23: 1 | H23: =(Assumptions!$B$5*$G23*$D23+Assumptions!$C$5*$G23*$F23)/1000000 | I23: =(Assumptions!$B$6*$G23*$D23+Assumptions!$C$6*$G23*$F23)/1000000 | J23: =(Assumptions!$B$7*$G23*$D23+Assumptions!$C$7*$G23*$F23)/1000000 | K23: =$I23*Assumptions!$B$10 | L23: =$I23*Assumptions!$B$11 | M23: =$I23*Assumptions!$B$12 | N23: =$I23/$I$35 | O23: - | P23: Yes - selectable (Google default) | R23: https://ai.google.dev/gemini-api/docs/pricing
A24: xAI | B24: grok-4.6 | C24: Balanced | D24: 2 | E24: 0.5 | F24: 6 | G24: 1 | H24: =(Assumptions!$B$5*$G24*$D24+Assumptions!$C$5*$G24*$F24)/1000000 | I24: =(Assumptions!$B$6*$G24*$D24+Assumptions!$C$6*$G24*$F24)/1000000 | J24: =(Assumptions!$B$7*$G24*$D24+Assumptions!$C$7*$G24*$F24)/1000000 | K24: =$I24*Assumptions!$B$10 | L24: =$I24*Assumptions!$B$11 | M24: =$I24*Assumptions!$B$12 | N24: =$I24/$I$35 | O24: 500k | P24: No - app lists only grok-3/grok-2 | Q24: Rates shown are <200k context. | R24: https://docs.x.ai/docs/models
A25: xAI | B25: grok-4.5 | C25: Balanced | D25: 2 | E25: 0.3 | F25: 6 | G25: 1 | H25: =(Assumptions!$B$5*$G25*$D25+Assumptions!$C$5*$G25*$F25)/1000000 | I25: =(Assumptions!$B$6*$G25*$D25+Assumptions!$C$6*$G25*$F25)/1000000 | J25: =(Assumptions!$B$7*$G25*$D25+Assumptions!$C$7*$G25*$F25)/1000000 | K25: =$I25*Assumptions!$B$10 | L25: =$I25*Assumptions!$B$11 | M25: =$I25*Assumptions!$B$12 | N25: =$I25/$I$35 | O25: 500k | P25: No - app lists only grok-3/grok-2 | Q25: Rates shown are <200k context. | R25: https://docs.x.ai/docs/models
A26: Alibaba (Qwen) | B26: qwen3.8-max | C26: Balanced | D26: 2 | E26: 0.25 | F26: 6 | G26: 1 | H26: =(Assumptions!$B$5*$G26*$D26+Assumptions!$C$5*$G26*$F26)/1000000 | I26: =(Assumptions!$B$6*$G26*$D26+Assumptions!$C$6*$G26*$F26)/1000000 | J26: =(Assumptions!$B$7*$G26*$D26+Assumptions!$C$7*$G26*$F26)/1000000 | K26: =$I26*Assumptions!$B$10 | L26: =$I26*Assumptions!$B$11 | M26: =$I26*Assumptions!$B$12 | N26: =$I26/$I$35 | O26: 1M | P26: No - new provider needed (OpenAI-compatible API via DashScope) | Q26: Chinese (Alibaba). Strongest Qwen model. | R26: https://www.eesel.ai/blog/qwen-pricing
A27: Anthropic | B27: Claude Sonnet 5 | C27: Balanced | D27: 2 | E27: 0.2 | F27: 10 | G27: 1 | H27: =(Assumptions!$B$5*$G27*$D27+Assumptions!$C$5*$G27*$F27)/1000000 | I27: =(Assumptions!$B$6*$G27*$D27+Assumptions!$C$6*$G27*$F27)/1000000 | J27: =(Assumptions!$B$7*$G27*$D27+Assumptions!$C$7*$G27*$F27)/1000000 | K27: =$I27*Assumptions!$B$10 | L27: =$I27*Assumptions!$B$11 | M27: =$I27*Assumptions!$B$12 | N27: =$I27/$I$35 | O27: 1M | P27: Yes - selectable (default), not yet tested on V5 | Q27: Batch API 50% off ($1 / $5). | R27: https://platform.claude.com/docs/en/about-claude/pricing
A28: OpenAI | B28: gpt-5.6-terra | C28: Balanced | D28: 2 | E28: 0.2 | F28: 12 | G28: 1 | H28: =(Assumptions!$B$5*$G28*$D28+Assumptions!$C$5*$G28*$F28)/1000000 | I28: =(Assumptions!$B$6*$G28*$D28+Assumptions!$C$6*$G28*$F28)/1000000 | J28: =(Assumptions!$B$7*$G28*$D28+Assumptions!$C$7*$G28*$F28)/1000000 | K28: =$I28*Assumptions!$B$10 | L28: =$I28*Assumptions!$B$11 | M28: =$I28*Assumptions!$B$12 | N28: =$I28/$I$35 | O28: - | P28: No - add id (provider exists) | R28: https://developers.openai.com/api/docs/pricing
A29: Google | B29: Gemini 3.1 Pro Preview | C29: Balanced | D29: 2 | E29: 0.2 | F29: 12 | G29: 1 | H29: =(Assumptions!$B$5*$G29*$D29+Assumptions!$C$5*$G29*$F29)/1000000 | I29: =(Assumptions!$B$6*$G29*$D29+Assumptions!$C$6*$G29*$F29)/1000000 | J29: =(Assumptions!$B$7*$G29*$D29+Assumptions!$C$7*$G29*$F29)/1000000 | K29: =$I29*Assumptions!$B$10 | L29: =$I29*Assumptions!$B$11 | M29: =$I29*Assumptions!$B$12 | N29: =$I29/$I$35 | O29: - | P29: No - add id (provider exists) | Q29: Preview model. Rates shown are <=200k context. | R29: https://ai.google.dev/gemini-api/docs/pricing
A30: OpenAI | B30: gpt-4o | C30: Balanced | D30: 2.5 | E30: 1.25 | F30: 10 | G30: 1 | H30: =(Assumptions!$B$5*$G30*$D30+Assumptions!$C$5*$G30*$F30)/1000000 | I30: =(Assumptions!$B$6*$G30*$D30+Assumptions!$C$6*$G30*$F30)/1000000 | J30: =(Assumptions!$B$7*$G30*$D30+Assumptions!$C$7*$G30*$F30)/1000000 | K30: =$I30*Assumptions!$B$10 | L30: =$I30*Assumptions!$B$11 | M30: =$I30*Assumptions!$B$12 | N30: =$I30/$I$35 | O30: - | P30: Yes - selectable (OpenAI default) | Q30: Older model. | R30: https://developers.openai.com/api/docs/pricing
A31: OpenAI | B31: gpt-5.4 | C31: Balanced | D31: 2.5 | E31: 0.25 | F31: 15 | G31: 1 | H31: =(Assumptions!$B$5*$G31*$D31+Assumptions!$C$5*$G31*$F31)/1000000 | I31: =(Assumptions!$B$6*$G31*$D31+Assumptions!$C$6*$G31*$F31)/1000000 | J31: =(Assumptions!$B$7*$G31*$D31+Assumptions!$C$7*$G31*$F31)/1000000 | K31: =$I31*Assumptions!$B$10 | L31: =$I31*Assumptions!$B$11 | M31: =$I31*Assumptions!$B$12 | N31: =$I31/$I$35 | O31: - | P31: No - add id (provider exists) | R31: https://developers.openai.com/api/docs/pricing
A32: Anthropic | B32: Claude Sonnet 4.6 | C32: Balanced | D32: 3 | E32: 0.3 | F32: 15 | G32: 1 | H32: =(Assumptions!$B$5*$G32*$D32+Assumptions!$C$5*$G32*$F32)/1000000 | I32: =(Assumptions!$B$6*$G32*$D32+Assumptions!$C$6*$G32*$F32)/1000000 | J32: =(Assumptions!$B$7*$G32*$D32+Assumptions!$C$7*$G32*$F32)/1000000 | K32: =$I32*Assumptions!$B$10 | L32: =$I32*Assumptions!$B$11 | M32: =$I32*Assumptions!$B$12 | N32: =$I32/$I$35 | O32: 1M | P32: Yes - selectable | Q32: Older tokenizer (~30% fewer tokens than Opus 5 for same text). | R32: https://platform.claude.com/docs/en/about-claude/pricing
A33: Moonshot (Kimi) | B33: kimi-k3 | C33: Balanced | D33: 3 | E33: 0.3 | F33: 15 | G33: 1 | H33: =(Assumptions!$B$5*$G33*$D33+Assumptions!$C$5*$G33*$F33)/1000000 | I33: =(Assumptions!$B$6*$G33*$D33+Assumptions!$C$6*$G33*$F33)/1000000 | J33: =(Assumptions!$B$7*$G33*$D33+Assumptions!$C$7*$G33*$F33)/1000000 | K33: =$I33*Assumptions!$B$10 | L33: =$I33*Assumptions!$B$11 | M33: =$I33*Assumptions!$B$12 | N33: =$I33/$I$35 | O33: 1M | P33: No - new provider needed (OpenAI-compatible API) | Q33: K3 has a separate cache-write price; not on Batch API. | R33: https://platform.kimi.ai/docs/pricing/chat
A34: OpenAI | B34: gpt-5.6-sol | C34: Premium | D34: 4 | E34: 0.4 | F34: 20 | G34: 1 | H34: =(Assumptions!$B$5*$G34*$D34+Assumptions!$C$5*$G34*$F34)/1000000 | I34: =(Assumptions!$B$6*$G34*$D34+Assumptions!$C$6*$G34*$F34)/1000000 | J34: =(Assumptions!$B$7*$G34*$D34+Assumptions!$C$7*$G34*$F34)/1000000 | K34: =$I34*Assumptions!$B$10 | L34: =$I34*Assumptions!$B$11 | M34: =$I34*Assumptions!$B$12 | N34: =$I34/$I$35 | O34: - | P34: No - add id (provider exists) | R34: https://developers.openai.com/api/docs/pricing
A35: Anthropic | B35: Claude Opus 5 | C35: Premium | D35: 5 | E35: 0.5 | F35: 25 | G35: 1 | H35: =(Assumptions!$B$5*$G35*$D35+Assumptions!$C$5*$G35*$F35)/1000000 | I35: =(Assumptions!$B$6*$G35*$D35+Assumptions!$C$6*$G35*$F35)/1000000 | J35: =(Assumptions!$B$7*$G35*$D35+Assumptions!$C$7*$G35*$F35)/1000000 | K35: =$I35*Assumptions!$B$10 | L35: =$I35*Assumptions!$B$11 | M35: =$I35*Assumptions!$B$12 | N35: =$I35/$I$35 | O35: 1M | P35: Yes - selectable, tested | Q35: Current V5 model. Batch API is 50% off ($2.50 / $12.50). | R35: https://platform.claude.com/docs/en/about-claude/pricing
A36: OpenAI | B36: gpt-5.5 | C36: Premium | D36: 5 | E36: 0.5 | F36: 30 | G36: 1 | H36: =(Assumptions!$B$5*$G36*$D36+Assumptions!$C$5*$G36*$F36)/1000000 | I36: =(Assumptions!$B$6*$G36*$D36+Assumptions!$C$6*$G36*$F36)/1000000 | J36: =(Assumptions!$B$7*$G36*$D36+Assumptions!$C$7*$G36*$F36)/1000000 | K36: =$I36*Assumptions!$B$10 | L36: =$I36*Assumptions!$B$11 | M36: =$I36*Assumptions!$B$12 | N36: =$I36/$I$35 | O36: - | P36: No - add id (provider exists) | R36: https://developers.openai.com/api/docs/pricing
A37: Anthropic | B37: Claude Fable 5.1 | C37: Premium | D37: 10 | E37: 0.25 | F37: 50 | G37: 1 | H37: =(Assumptions!$B$5*$G37*$D37+Assumptions!$C$5*$G37*$F37)/1000000 | I37: =(Assumptions!$B$6*$G37*$D37+Assumptions!$C$6*$G37*$F37)/1000000 | J37: =(Assumptions!$B$7*$G37*$D37+Assumptions!$C$7*$G37*$F37)/1000000 | K37: =$I37*Assumptions!$B$10 | L37: =$I37*Assumptions!$B$11 | M37: =$I37*Assumptions!$B$12 | N37: =$I37/$I$35 | O37: 1M | P37: Add id claude-fable-5-1 (claude-fable-5 is selectable, same price) | R37: https://platform.claude.com/docs/en/about-claude/pricing
A38: OpenAI | B38: gpt-6-astra | C38: Premium | D38: 10 | E38: 1 | F38: 50 | G38: 1 | H38: =(Assumptions!$B$5*$G38*$D38+Assumptions!$C$5*$G38*$F38)/1000000 | I38: =(Assumptions!$B$6*$G38*$D38+Assumptions!$C$6*$G38*$F38)/1000000 | J38: =(Assumptions!$B$7*$G38*$D38+Assumptions!$C$7*$G38*$F38)/1000000 | K38: =$I38*Assumptions!$B$10 | L38: =$I38*Assumptions!$B$11 | M38: =$I38*Assumptions!$B$12 | N38: =$I38/$I$35 | O38: - | P38: No - add id (provider exists) | R38: https://developers.openai.com/api/docs/pricing
